{"Alloc":{"count":0,"gauge":3694760},"BuckHashSys":{"count":0,"gauge":3929},"Frees":{"count":0,"gauge":143},"GCCPUFraction":{"count":0,"gauge":0},"GCSys":{"count":0,"gauge":7085080},"GetSet173":{"count":0,"gauge":117977.50139893651},"GetSet44":{"count":780184143,"gauge":0},"HeapAlloc":{"count":0,"gauge":3694760},"HeapIdle":{"count":0,"gauge":3743744},"HeapInuse":{"count":0,"gauge":4382720},"HeapObjects":{"count":0,"gauge":1597},"HeapReleased":{"count":0,"gauge":3702784},"HeapSys":{"count":0,"gauge":8126464},"LastGC":{"count":0,"gauge":0},"Lookups":{"count":0,"gauge":0},"MCacheInuse":{"count":0,"gauge":4800},"MCacheSys":{"count":0,"gauge":15600},"MSpanInuse":{"count":0,"gauge":34080},"MSpanSys":{"count":0,"gauge":48960},"Mallocs":{"count":0,"gauge":1740},"NextGC":{"count":0,"gauge":4194304},"NumForcedGC":{"count":0,"gauge":0},"NumGC":{"count":0,"gauge":0},"OtherSys":{"count":0,"gauge":840815},"PauseTotalNs":{"count":0,"gauge":0},"PollCount":{"count":70,"gauge":0},"RandomValue":{"count":0,"gauge":0.8109317228874247},"StackInuse":{"count":0,"gauge":262144},"StackSys":{"count":0,"gauge":262144},"Sys":{"count":0,"gauge":16382992},"TotalAlloc":{"count":0,"gauge":3694760}}
